plstab/__init__.py
plstab/assets/c0.png
plstab/assets/c1.png
plstab/assets/c2.png
plstab/assets/c3.png
plstab/assets/cloud.png
plstab/assets/f35.png
plstab/assets/jet.png
plstab/env/__init__.py
plstab/env/aerodynamics.py
plstab/env/assets/c0.png
plstab/env/assets/c1.png
plstab/env/assets/c2.png
plstab/env/assets/c3.png
plstab/env/assets/cloud.png
plstab/env/assets/f35.png
plstab/env/assets/jet.png
plstab/env/drive_unit.py
plstab/env/dynamics.py
plstab/env/plane_env.py
plstab/env/visplane2.py
plstab/env/wind.py
plstab-0.1.0.dist-info/METADATA
plstab-0.1.0.dist-info/WHEEL
plstab-0.1.0.dist-info/RECORD
