Metadata-Version: 2.1
Name: plstab
Version: 0.1.0
Summary: 
Author: Maly
Author-email: swampinhabitant@icloud.com
Requires-Python: >=3.10,<4.0
Classifier: Programming Language :: Python :: 3
Classifier: Programming Language :: Python :: 3.10
Classifier: Programming Language :: Python :: 3.11
Classifier: Programming Language :: Python :: 3.12
Requires-Dist: gymnasium (>=0.29.1,<0.30.0)
Requires-Dist: matplotlib (>=3.8.4,<4.0.0)
Requires-Dist: numpy (>=1.26.4,<2.0.0)
Requires-Dist: pygame (>=2.5.2,<3.0.0)
Requires-Dist: pyqt6 (>=6.7.0,<7.0.0)
Requires-Dist: scipy (>=1.13.0,<2.0.0)
